physicalrisk
