Metadata-Version: 2.1
Name: physicalrisk
Version: 0.1.9
Summary: A climate physical value at risk calculator
Home-page: UNKNOWN
Author: Rupert Xu
Author-email: rupert.xu@blockchainclimate.org
License: MIT
Keywords: climate physical risk
Platform: UNKNOWN
Classifier: Development Status :: 5 - Production/Stable
Classifier: Intended Audience :: Education
Classifier: Operating System :: Microsoft :: Windows :: Windows 10
Classifier: License :: OSI Approved :: MIT License
Classifier: Programming Language :: Python :: 3
